{"Coins":[{"Symbol":"BTC","ForeignName":"BTCUSD","Exchange":"ByBit","Ignore":true},{"Symbol":"ETH","ForeignName":"ETHUSD","Exchange":"ByBit","Ignore":true},{"Symbol":"EOS","ForeignName":"EOSUSD","Exchange":"ByBit","Ignore":true},{"Symbol":"XRP","ForeignName":"XRPUSD","Exchange":"ByBit","Ignore":true},{"Symbol":"DOT","ForeignName":"DOTUSD","Exchange":"ByBit","Ignore":true},{"Symbol":"BIT","ForeignName":"BITUSD","Exchange":"ByBit","Ignore":true},{"Symbol":"BTC","ForeignName":"BTCUSDT","Exchange":"ByBit","Ignore":true},{"Symbol":"ETH","ForeignName":"ETHUSDT","Exchange":"ByBit","Ignore":true},{"Symbol":"EOS","ForeignName":"EOSUSDT","Exchange":"ByBit","Ignore":true},{"Symbol":"XRP","ForeignName":"XRPUSDT","Exchange":"ByBit","Ignore":true},{"Symbol":"BCH","ForeignName":"BCHUSDT","Exchange":"ByBit","Ignore":true},{"Symbol":"LTC","ForeignName":"LTCUSDT","Exchange":"ByBit","Ignore":true},{"Symbol":"XTZ","ForeignName":"XTZUSDT","Exchange":"ByBit","Ignore":true},{"Symbol":"LINK","ForeignName":"LINKUSDT","Exchange":"ByBit","Ignore":true},{"Symbol":"ADA","ForeignName":"ADAUSDT","Exchange":"ByBit","Ignore":true},{"Symbol":"DOT","ForeignName":"DOTUSDT","Exchange":"ByBit","Ignore":true},{"Symbol":"UNI","ForeignName":"UNIUSDT","Exchange":"ByBit","Ignore":true},{"Symbol":"XEM","ForeignName":"XEMUSDT","Exchange":"ByBit","Ignore":true},{"Symbol":"SUSHI","ForeignName":"SUSHIUSDT","Exchange":"ByBit","Ignore":true},{"Symbol":"AAVE","ForeignName":"AAVEUSDT","Exchange":"ByBit","Ignore":true},{"Symbol":"DOGE","ForeignName":"DOGEUSDT","Exchange":"ByBit","Ignore":true},{"Symbol":"MATIC","ForeignName":"MATICUSDT","Exchange":"ByBit","Ignore":true},{"Symbol":"ETC","ForeignName":"ETCUSDT","Exchange":"ByBit","Ignore":true},{"Symbol":"BNB","ForeignName":"BNBUSDT","Exchange":"ByBit","Ignore":true},{"Symbol":"FIL","ForeignName":"FILUSDT","Exchange":"ByBit","Ignore":true},{"Symbol":"SOL","ForeignName":"SOLUSDT","Exchange":"ByBit","Ignore":true},{"Symbol":"XLM","ForeignName":"XLMUSDT","Exchange":"ByBit","Ignore":true},{"Symbol":"TRX","ForeignName":"TRXUSDT","Exchange":"ByBit","Ignore":true},{"Symbol":"VET","ForeignName":"VETUSDT","Exchange":"ByBit","Ignore":true},{"Symbol":"THETA","ForeignName":"THETAUSDT","Exchange":"ByBit","Ignore":true},{"Symbol":"COMP","ForeignName":"COMPUSDT","Exchange":"ByBit","Ignore":true},{"Symbol":"AXS","ForeignName":"AXSUSDT","Exchange":"ByBit","Ignore":true},{"Symbol":"LUNA","ForeignName":"LUNAUSDT","Exchange":"ByBit","Ignore":true},{"Symbol":"SAND","ForeignName":"SANDUSDT","Exchange":"ByBit","Ignore":true},{"Symbol":"MANA","ForeignName":"MANAUSDT","Exchange":"ByBit","Ignore":true},{"Symbol":"KSM","ForeignName":"KSMUSDT","Exchange":"ByBit","Ignore":true},{"Symbol":"ATOM","ForeignName":"ATOMUSDT","Exchange":"ByBit","Ignore":true},{"Symbol":"AVAX","ForeignName":"AVAXUSDT","Exchange":"ByBit","Ignore":true},{"Symbol":"CHZ","ForeignName":"CHZUSDT","Exchange":"ByBit","Ignore":true},{"Symbol":"CRV","ForeignName":"CRVUSDT","Exchange":"ByBit","Ignore":true},{"Symbol":"ENJ","ForeignName":"ENJUSDT","Exchange":"ByBit","Ignore":true},{"Symbol":"GRT","ForeignName":"GRTUSDT","Exchange":"ByBit","Ignore":true},{"Symbol":"SHIB1000","ForeignName":"SHIB1000USDT","Exchange":"ByBit","Ignore":true},{"Symbol":"YFI","ForeignName":"YFIUSDT","Exchange":"ByBit","Ignore":true},{"Symbol":"BSV","ForeignName":"BSVUSDT","Exchange":"ByBit","Ignore":true},{"Symbol":"ICP","ForeignName":"ICPUSDT","Exchange":"ByBit","Ignore":true},{"Symbol":"FTM","ForeignName":"FTMUSDT","Exchange":"ByBit","Ignore":true},{"Symbol":"ALGO","ForeignName":"ALGOUSDT","Exchange":"ByBit","Ignore":true},{"Symbol":"DYDX","ForeignName":"DYDXUSDT","Exchange":"ByBit","Ignore":true},{"Symbol":"NEAR","ForeignName":"NEARUSDT","Exchange":"ByBit","Ignore":true},{"Symbol":"SRM","ForeignName":"SRMUSDT","Exchange":"ByBit","Ignore":true},{"Symbol":"OMG","ForeignName":"OMGUSDT","Exchange":"ByBit","Ignore":true},{"Symbol":"IOST","ForeignName":"IOSTUSDT","Exchange":"ByBit","Ignore":true},{"Symbol":"DASH","ForeignName":"DASHUSDT","Exchange":"ByBit","Ignore":true},{"Symbol":"FTT","ForeignName":"FTTUSDT","Exchange":"ByBit","Ignore":true},{"Symbol":"BIT","ForeignName":"BITUSDT","Exchange":"ByBit","Ignore":true},{"Symbol":"GALA","ForeignName":"GALAUSDT","Exchange":"ByBit","Ignore":true},{"Symbol":"CELR","ForeignName":"CELRUSDT","Exchange":"ByBit","Ignore":true},{"Symbol":"HBAR","ForeignName":"HBARUSDT","Exchange":"ByBit","Ignore":true},{"Symbol":"ONE","ForeignName":"ONEUSDT","Exchange":"ByBit","Ignore":true},{"Symbol":"C98","ForeignName":"C98USDT","Exchange":"ByBit","Ignore":true},{"Symbol":"COTI","ForeignName":"COTIUSDT","Exchange":"ByBit","Ignore":true},{"Symbol":"ALICE","ForeignName":"ALICEUSDT","Exchange":"ByBit","Ignore":true},{"Symbol":"EGLD","ForeignName":"EGLDUSDT","Exchange":"ByBit","Ignore":true},{"Symbol":"REN","ForeignName":"RENUSDT","Exchange":"ByBit","Ignore":true},{"Symbol":"KEEP","ForeignName":"KEEPUSDT","Exchange":"ByBit","Ignore":true},{"Symbol":"TLM","ForeignName":"TLMUSDT","Exchange":"ByBit","Ignore":true},{"Symbol":"RUNE","ForeignName":"RUNEUSDT","Exchange":"ByBit","Ignore":true},{"Symbol":"ILV","ForeignName":"ILVUSDT","Exchange":"ByBit","Ignore":true},{"Symbol":"FLOW","ForeignName":"FLOWUSDT","Exchange":"ByBit","Ignore":true},{"Symbol":"WOO","ForeignName":"WOOUSDT","Exchange":"ByBit","Ignore":true},{"Symbol":"LRC","ForeignName":"LRCUSDT","Exchange":"ByBit","Ignore":true},{"Symbol":"ENS","ForeignName":"ENSUSDT","Exchange":"ByBit","Ignore":true},{"Symbol":"IOTX","ForeignName":"IOTXUSDT","Exchange":"ByBit","Ignore":true},{"Symbol":"CHR","ForeignName":"CHRUSDT","Exchange":"ByBit","Ignore":true},{"Symbol":"BAT","ForeignName":"BATUSDT","Exchange":"ByBit","Ignore":true},{"Symbol":"STORJ","ForeignName":"STORJUSDT","Exchange":"ByBit","Ignore":true},{"Symbol":"SNX","ForeignName":"SNXUSDT","Exchange":"ByBit","Ignore":true},{"Symbol":"SLP","ForeignName":"SLPUSDT","Exchange":"ByBit","Ignore":true},{"Symbol":"ANKR","ForeignName":"ANKRUSDT","Exchange":"ByBit","Ignore":true},{"Symbol":"LPT","ForeignName":"LPTUSDT","Exchange":"ByBit","Ignore":true},{"Symbol":"QTUM","ForeignName":"QTUMUSDT","Exchange":"ByBit","Ignore":true},{"Symbol":"CRO","ForeignName":"CROUSDT","Exchange":"ByBit","Ignore":true},{"Symbol":"SXP","ForeignName":"SXPUSDT","Exchange":"ByBit","Ignore":true},{"Symbol":"YGG","ForeignName":"YGGUSDT","Exchange":"ByBit","Ignore":true},{"Symbol":"ZEC","ForeignName":"ZECUSDT","Exchange":"ByBit","Ignore":true},{"Symbol":"IMX","ForeignName":"IMXUSDT","Exchange":"ByBit","Ignore":true},{"Symbol":"SFP","ForeignName":"SFPUSDT","Exchange":"ByBit","Ignore":true},{"Symbol":"AUDIO","ForeignName":"AUDIOUSDT","Exchange":"ByBit","Ignore":true},{"Symbol":"ZEN","ForeignName":"ZENUSDT","Exchange":"ByBit","Ignore":true},{"Symbol":"BTT","ForeignName":"BTTUSDT","Exchange":"ByBit","Ignore":true},{"Symbol":"GTC","ForeignName":"GTCUSDT","Exchange":"ByBit","Ignore":true},{"Symbol":"LIT","ForeignName":"LITUSDT","Exchange":"ByBit","Ignore":true},{"Symbol":"CVC","ForeignName":"CVCUSDT","Exchange":"ByBit","Ignore":true},{"Symbol":"RNDR","ForeignName":"RNDRUSDT","Exchange":"ByBit","Ignore":true},{"Symbol":"SC","ForeignName":"SCUSDT","Exchange":"ByBit","Ignore":true},{"Symbol":"RSR","ForeignName":"RSRUSDT","Exchange":"ByBit","Ignore":true},{"Symbol":"STX","ForeignName":"STXUSDT","Exchange":"ByBit","Ignore":true},{"Symbol":"MASK","ForeignName":"MASKUSDT","Exchange":"ByBit","Ignore":true},{"Symbol":"CTK","ForeignName":"CTKUSDT","Exchange":"ByBit","Ignore":true},{"Symbol":"BICO","ForeignName":"BICOUSDT","Exchange":"ByBit","Ignore":true},{"Symbol":"REQ","ForeignName":"REQUSDT","Exchange":"ByBit","Ignore":true},{"Symbol":"1INCH","ForeignName":"1INCHUSDT","Exchange":"ByBit","Ignore":true},{"Symbol":"KLAY","ForeignName":"KLAYUSDT","Exchange":"ByBit","Ignore":true},{"Symbol":"SPELL","ForeignName":"SPELLUSDT","Exchange":"ByBit","Ignore":true},{"Symbol":"ANT","ForeignName":"ANTUSDT","Exchange":"ByBit","Ignore":true},{"Symbol":"DUSK","ForeignName":"DUSKUSDT","Exchange":"ByBit","Ignore":true},{"Symbol":"AR","ForeignName":"ARUSDT","Exchange":"ByBit","Ignore":true},{"Symbol":"PEOPLE","ForeignName":"PEOPLEUSDT","Exchange":"ByBit","Ignore":true},{"Symbol":"IOTA","ForeignName":"IOTAUSDT","Exchange":"ByBit","Ignore":true},{"Symbol":"CELO","ForeignName":"CELOUSDT","Exchange":"ByBit","Ignore":true},{"Symbol":"WAVES","ForeignName":"WAVESUSDT","Exchange":"ByBit","Ignore":true},{"Symbol":"RVN","ForeignName":"RVNUSDT","Exchange":"ByBit","Ignore":true},{"Symbol":"BTC","ForeignName":"BTCUSDM22","Exchange":"ByBit","Ignore":true},{"Symbol":"BTC","ForeignName":"BTCUSDH22","Exchange":"ByBit","Ignore":true},{"Symbol":"ETH","ForeignName":"ETHUSDM22","Exchange":"ByBit","Ignore":true},{"Symbol":"ETH","ForeignName":"ETHUSDH22","Exchange":"ByBit","Ignore":true}]}